seven2one/__init__.py
seven2one/authentication.py
seven2one/authorization.py
seven2one/automation.py
seven2one/config.json
seven2one/core.py
seven2one/core_config.py
seven2one/core_interface.py
seven2one/core_metadata.py
seven2one/dynamicobjects.py
seven2one/dynamicobjects_interface.py
seven2one/email.py
seven2one/fileimport.py
seven2one/logging_loki/README.md
seven2one/logging_loki/__init__.py
seven2one/logging_loki/const.py
seven2one/logging_loki/emitter.py
seven2one/logging_loki/handlers.py
seven2one/programming.py
seven2one/schedule.py
seven2one/timeseries.py
seven2one/timeseries_interface.py
seven2one/utils/__init__.py
seven2one/utils/defaults.py
seven2one/utils/ut_autom_enums.py
seven2one/utils/ut_autprog.py
seven2one/utils/ut_client.py
seven2one/utils/ut_data_frame.py
seven2one/utils/ut_device_client.py
seven2one/utils/ut_error_handler.py
seven2one/utils/ut_fileimport.py
seven2one/utils/ut_graphql.py
seven2one/utils/ut_log.py
seven2one/utils/ut_meta.py
seven2one/utils/ut_order.py
seven2one/utils/ut_property.py
seven2one/utils/ut_structure.py
seven2one/utils/ut_time.py
seven2one/utils/ut_timeseries.py
seven2one/utils/ut_timezone.py
seven2one/workflow.py
seven2one-9.3.1.dist-info/METADATA
seven2one-9.3.1.dist-info/WHEEL
seven2one-9.3.1.dist-info/licenses/LICENSE
seven2one-9.3.1.dist-info/RECORD
