Metadata-Version: 2.4
Name: seven2one
Version: 9.3.1
Summary: Functions to interact with the Seven2one TechStack
License: MIT
License-File: LICENSE
Author: Seven2one Informationssysteme GmbH
Author-email: info@seven2one.de
Requires-Python: >=3.10,<4.0
Classifier: Development Status :: 5 - Production/Stable
Classifier: License :: OSI Approved :: MIT License
Classifier: Natural Language :: English
Classifier: Operating System :: OS Independent
Classifier: Programming Language :: Python :: 3
Classifier: Programming Language :: Python :: 3.10
Classifier: Programming Language :: Python :: 3.11
Classifier: Programming Language :: Python :: 3.12
Classifier: Programming Language :: Python :: 3.13
Classifier: Programming Language :: Python :: 3.14
Requires-Dist: gql (==3.0.0)
Requires-Dist: loguru (==0.7.2)
Requires-Dist: numpy (>=1.26.0,<2.0.0)
Requires-Dist: pandas (>=1.5.3,<2.0.0)
Requires-Dist: pika (==1.3.2)
Requires-Dist: pyperclip (==1.9.0)
Requires-Dist: pytz (==2024.1)
Requires-Dist: requests (==2.32.3)
Requires-Dist: requests-oauthlib (==2.0.0)
Requires-Dist: requests-toolbelt (==1.0.0)
Requires-Dist: rfc3339 (==6.2)
Requires-Dist: tzlocal (==5.2)
Project-URL: Homepage, http://www.seven2one.de
